{
  "manifest": {
    "id": "system.limax.local",
    "name": "Limax",
    "version": "1.0.0",
    "author": "Shellex",
    "description": "The local-first Shellex package manager for vault apps.",
    "repository": "https://github.com/elmirok/shellex-limax",
    "type": "system-app",
    "entry": "README.md",
    "runtime": "host",
    "permissions": [
      "apps:list",
      "apps:install",
      "apps:remove"
    ],
    "window": {
      "width": 820,
      "height": 620,
      "resizable": true
    }
  },
  "files": {
    "README.md": "# Limax\n\nLimax is the Shellex OS package manager app and command.\n\nCurrent MVP: local `.sapp` install, installed package listing, package info, package removal, source repository records and repo update checks.\n\nRun `limax help` in Shell for usage."
  }
}
